client/__init__.py
client/add_contact.py
client/chat_window_conv.py
client/client_chat.py
client/client_chat_conv.py
client/client_contacts.py
client/client_contacts_conv.py
client/database.py
client/del_contact.py
client/start_dialog.py
common_client/__init__.py
common_client/client_core.py
common_client/decos.py
common_client/errors.py
common_client/utils.py
common_client/variables.py
logs_client/__init__.py
logs_client/config_client_log.py
message_client_march_ru-0.1.dist-info/METADATA
message_client_march_ru-0.1.dist-info/WHEEL
message_client_march_ru-0.1.dist-info/top_level.txt
message_client_march_ru-0.1.dist-info/RECORD
