Metadata-Version: 2.1
Name: message-client-march-ru
Version: 0.1
Summary: Client packet
Author: student_forever
Author-email: test@yandex.ru
License: UNKNOWN
Platform: UNKNOWN
Requires-Dist: PyQt5
Requires-Dist: sqlalchemy
Requires-Dist: pycryptodome
Requires-Dist: pycryptodomex
